namuwiki/__init__.py
namuwiki/_syntax.py
namuwiki/extractor.py
namuwiki/macros.py
namu_wiki_extractor-0.3.0.dist-info/LICENSE
namu_wiki_extractor-0.3.0.dist-info/METADATA
namu_wiki_extractor-0.3.0.dist-info/WHEEL
namu_wiki_extractor-0.3.0.dist-info/top_level.txt
namu_wiki_extractor-0.3.0.dist-info/RECORD
