Metadata-Version: 2.1
Name: namu-wiki-extractor
Version: 0.3.0
Summary: A library to extract plaintexts from the namu wiki dump
Home-page: https://github.com/jonghwanhyeon/namu-wiki-extractor
Author: Jonghwan Hyeon
Author-email: hyeon0145@gmail.com
License: MIT
Keywords: namu wiki plaintext extractor
Classifier: Development Status :: 4 - Beta
Classifier: Intended Audience :: Developers
Classifier: Intended Audience :: Science/Research
Classifier: License :: OSI Approved :: MIT License
Classifier: Topic :: Scientific/Engineering :: Artificial Intelligence
Classifier: Topic :: Scientific/Engineering :: Information Analysis
Classifier: Topic :: Text Processing :: Markup
Classifier: Programming Language :: Python :: 3
Classifier: Programming Language :: Python :: 3.0
Classifier: Programming Language :: Python :: 3.1
Classifier: Programming Language :: Python :: 3.2
Classifier: Programming Language :: Python :: 3.3
Classifier: Programming Language :: Python :: 3.4
Classifier: Programming Language :: Python :: 3.5
Classifier: Programming Language :: Python :: 3.6
Classifier: Programming Language :: Python :: 3 :: Only
License-File: LICENSE
